pgfinder/__init__.py
pgfinder/default_config.yaml
pgfinder/errors.py
pgfinder/find_pg.py
pgfinder/matching.py
pgfinder/pgio.py
pgfinder/utils.py
pgfinder/validation.py
pgfinder/config/allowed_modifications.txt
pgfinder/config/columns.yaml
pgfinder/config/parameters.yaml
pgfinder/gui/__init__.py
pgfinder/gui/internal.py
pgfinder/gui/shim.py
pgfinder/logs/__init__.py
pgfinder/logs/logs.py
pgfinder/masses/c_diff_monomers_complex.csv
pgfinder/masses/c_diff_monomers_non_redundant.csv
pgfinder/masses/c_diff_monomers_simple.csv
pgfinder/masses/e_coli_monomers_complex.csv
pgfinder/masses/e_coli_monomers_non_redundant.csv
pgfinder/masses/e_coli_monomers_simple.csv
pgfinder/masses/index.json
pgfinder-1.3.1.dist-info/METADATA
pgfinder-1.3.1.dist-info/WHEEL
pgfinder-1.3.1.dist-info/entry_points.txt
pgfinder-1.3.1.dist-info/top_level.txt
pgfinder-1.3.1.dist-info/RECORD
